lascheck/__init__.py
lascheck/defaults.py
lascheck/exceptions.py
lascheck/las.py
lascheck/las_items.py
lascheck/reader.py
lascheck/spec.py
lascheck-0.1.5.dist-info/LICENSE
lascheck-0.1.5.dist-info/METADATA
lascheck-0.1.5.dist-info/WHEEL
lascheck-0.1.5.dist-info/top_level.txt
lascheck-0.1.5.dist-info/RECORD
