Metadata-Version: 2.1
Name: lascheck
Version: 0.1.5
Summary: Checking conformity of Log ASCII Standard (LAS) files to LAS 2.0 standard
Home-page: https://github.com/MandarJKulkarni/lascheck
Author: Mandar J Kulkarni.
Author-email: "Mandar J Kulkarni." <mjkool@gmail.com>
License: MIT License
Project-URL: Homepage, https://github.com/MandarJKulkarni/lascheck
Project-URL: Issues, https://github.com/MandarJKulkarni/lascheck/issues
Keywords: las,geophysics,version
Classifier: Development Status :: 4 - Beta
Classifier: Environment :: Console
Classifier: Intended Audience :: Developers
Classifier: Intended Audience :: Education
Classifier: Intended Audience :: End Users/Desktop
Classifier: Intended Audience :: Other Audience
Classifier: Intended Audience :: Science/Research
Classifier: License :: OSI Approved :: MIT License
Classifier: Natural Language :: English
Classifier: Operating System :: OS Independent
Classifier: Programming Language :: Python :: 3.7
Classifier: Topic :: Scientific/Engineering
Classifier: Topic :: System :: Filesystems
Classifier: Topic :: Scientific/Engineering :: Information Analysis
Requires-Python: >=3.5
License-File: LICENSE
